langsmith/__init__.py
langsmith/cli/__init__.py
langsmith/cli/docker-compose.beta.yaml
langsmith/cli/docker-compose.dev.yaml
langsmith/cli/docker-compose.ngrok.yaml
langsmith/cli/docker-compose.yaml
langsmith/cli/main.py
langsmith/cli/nginx.conf
langsmith/client.py
langsmith/env.py
langsmith/evaluation/__init__.py
langsmith/evaluation/evaluator.py
langsmith/evaluation/string_evaluator.py
langsmith/py.typed
langsmith/run_helpers.py
langsmith/run_trees.py
langsmith/schemas.py
langsmith/utils.py
ragstack_ai_langsmith-0.0.1a1.dist-info/METADATA
ragstack_ai_langsmith-0.0.1a1.dist-info/WHEEL
ragstack_ai_langsmith-0.0.1a1.dist-info/entry_points.txt
ragstack_ai_langsmith-0.0.1a1.dist-info/RECORD
