Metadata-Version: 2.1
Name: ragstack-ai-langsmith
Version: 0.0.1a1
Summary: Client library to connect to the LangSmith LLM Tracing and Evaluation Platform.
License: MIT
Keywords: langsmith,langchain,llm,nlp,language,translation,evaluation,tracing,platform
Author: DataStax
Requires-Python: >=3.8.1,<4.0
Classifier: License :: OSI Approved :: MIT License
Classifier: Programming Language :: Python :: 3
Classifier: Programming Language :: Python :: 3.9
Classifier: Programming Language :: Python :: 3.10
Classifier: Programming Language :: Python :: 3.11
Requires-Dist: pydantic (>=1,<3)
Requires-Dist: pytest-subtests (>=0.11.0,<0.12.0)
Requires-Dist: requests (>=2,<3)
